exoml/__init__.py
exoml/curve_prioritizer/__init__.py
exoml/curve_prioritizer/curve_prioritizer_generator.py
exoml/curve_prioritizer/curve_prioritizer_model.py
exoml/detrend/DETREND.py
exoml/detrend/__init__.py
exoml/detrend/detrend_generator.py
exoml/ete6/NanException.py
exoml/ete6/__init__.py
exoml/ete6/ete6_generator.py
exoml/haunter/__init__.py
exoml/haunter/haunter.py
exoml/haunter/haunter_generator.py
exoml/iatson/IATSON.py
exoml/iatson/IATSON_og.py
exoml/iatson/IATSON_planet.py
exoml/iatson/__init__.py
exoml/iatson/iatson_generator.py
exoml/iatson/iatson_og_generator.py
exoml/iatson/iatson_planet_generator.py
exoml/iatson/watson_planet_generator.py
exoml/ml/__init__.py
exoml/ml/ml_data_generator.py
exoml/ml/ml_single_transits_classifier.py
exoml/ml/thread_config.py
exoml/ml/calibration/__init__.py
exoml/ml/calibration/calibrator.py
exoml/ml/calibration/utils.py
exoml/ml/callback/__init__.py
exoml/ml/callback/auc.py
exoml/ml/callback/basemodel_aware_callback.py
exoml/ml/callback/batch_aware_csv_logger.py
exoml/ml/callback/checkpoint.py
exoml/ml/callback/early_stopping.py
exoml/ml/callback/get_weights.py
exoml/ml/callback/learning_rate.py
exoml/ml/callback/model_adapter.py
exoml/ml/callback/training_data_aware.py
exoml/ml/encoding/__init__.py
exoml/ml/encoding/time_position.py
exoml/ml/functions/__init__.py
exoml/ml/functions/functions.py
exoml/ml/layers/__init__.py
exoml/ml/layers/branch_dropout.py
exoml/ml/layers/dropout.py
exoml/ml/layers/random_reverse.py
exoml/ml/layers/transformer.py
exoml/ml/layers/transformer_classifier.py
exoml/ml/learning_rate/__init__.py
exoml/ml/learning_rate/schedulers.py
exoml/ml/log/__init__.py
exoml/ml/log/get_weights_logger.py
exoml/ml/log/with_logging.py
exoml/ml/loss/__init__.py
exoml/ml/loss/cross_entropy.py
exoml/ml/loss/unsupervised.py
exoml/ml/metrics/__init__.py
exoml/ml/metrics/auc.py
exoml/ml/metrics/fixed_mean.py
exoml/ml/model/__init__.py
exoml/ml/model/base_model.py
exoml/ml/model/binary_model.py
exoml-1.3.2.dist-info/METADATA
exoml-1.3.2.dist-info/WHEEL
exoml-1.3.2.dist-info/top_level.txt
exoml-1.3.2.dist-info/RECORD
