Metadata-Version: 2.4
Name: exoml
Version: 1.3.2
Summary: ExoML tools for exoplanet detections
Author-email: Martín Dévora-Pajares <mdevorapajares@protonmail.com>
License: MIT
Requires-Python: >=3.11
Requires-Dist: tensorflow==2.19.0
Requires-Dist: keras_nlp==0.21.1
Requires-Dist: lcbuilder==0.25.4
Requires-Dist: ruamel.yaml==0.17.32
Requires-Dist: pydot==1.4.2
Requires-Dist: graphviz==0.20.1
Requires-Dist: scikit-learn==1.7.0
Requires-Dist: typeguard==4.1.5
